who_calls/cli.py
who_calls/who_calls.py
who_calls-0.2.0.dist-info/METADATA
who_calls-0.2.0.dist-info/WHEEL
who_calls-0.2.0.dist-info/entry_points.txt
who_calls-0.2.0.dist-info/RECORD
