Metadata-Version: 2.4
Name: who-calls
Version: 0.2.0
Summary: Static caller-tree explorer for Python code
Author-email: JeyBee <janbjorge@gmail.com>
License: MIT
Requires-Python: >=3.11
Requires-Dist: networkx>=3.0
